axopy/__init__.py
axopy/daq.py
axopy/design.py
axopy/experiment.py
axopy/messaging.py
axopy/storage.py
axopy/timing.py
axopy/util.py
axopy/version.py
axopy/features/__init__.py
axopy/features/time.py
axopy/features/util.py
axopy/gui/__init__.py
axopy/gui/canvas.py
axopy/gui/graph.py
axopy/gui/main.py
axopy/gui/prompts.py
axopy/pipeline/__init__.py
axopy/pipeline/common.py
axopy/pipeline/core.py
axopy/pipeline/sources.py
axopy/task/__init__.py
axopy/task/base.py
axopy/task/common.py
axopy-0.2.3.dist-info/LICENSE
axopy-0.2.3.dist-info/METADATA
axopy-0.2.3.dist-info/WHEEL
axopy-0.2.3.dist-info/top_level.txt
axopy-0.2.3.dist-info/RECORD
