Metadata-Version: 2.1
Name: axopy
Version: 0.2.3
Summary: Human-computer interface experimentation library
Home-page: https://github.com/axopy/axopy
Author: Kenneth Lyons
Author-email: ixjlyons@gmail.com
License: MIT
Keywords: human computer interface control electrophysiology
Platform: UNKNOWN
Classifier: Development Status :: 4 - Beta
Classifier: License :: OSI Approved :: MIT License
Classifier: Environment :: X11 Applications :: Qt
Classifier: Intended Audience :: Science/Research
Classifier: Operating System :: OS Independent
Classifier: Topic :: Scientific/Engineering :: Human Machine Interfaces
Classifier: Topic :: Scientific/Engineering :: Medical Science Apps.
Classifier: Programming Language :: Python :: 2
Classifier: Programming Language :: Python :: 2.7
Classifier: Programming Language :: Python :: 3
Classifier: Programming Language :: Python :: 3.4
Classifier: Programming Language :: Python :: 3.5
Classifier: Programming Language :: Python :: 3.6
Requires-Dist: numpy
Requires-Dist: scipy
Requires-Dist: pandas
Requires-Dist: h5py
Requires-Dist: pyqt5
Requires-Dist: pyqtgraph (>=0.10)
Provides-Extra: dev
Requires-Dist: numpy ; extra == 'dev'
Requires-Dist: scipy ; extra == 'dev'
Requires-Dist: pandas ; extra == 'dev'
Requires-Dist: h5py ; extra == 'dev'
Requires-Dist: pyqt5 ; extra == 'dev'
Requires-Dist: pyqtgraph (>=0.10) ; extra == 'dev'
Requires-Dist: pytest (>=3.6) ; extra == 'dev'
Requires-Dist: pytest-cov ; extra == 'dev'
Requires-Dist: pytest-qt ; extra == 'dev'
Requires-Dist: pytest-mock ; extra == 'dev'
Requires-Dist: pytest-xvfb ; extra == 'dev'
Requires-Dist: flake8 ; extra == 'dev'
Requires-Dist: sphinx ; extra == 'dev'
Requires-Dist: sphinx-rtd-theme ; extra == 'dev'
Requires-Dist: sphinx-gallery ; extra == 'dev'
Requires-Dist: matplotlib ; extra == 'dev'
Requires-Dist: pillow ; extra == 'dev'
